[{"page":1931,"x":2,"y":2,"ans":"100\/11\/07"},{"page":1931,"x":2,"y":3,"ans":"\u500b\u4eba\u6350\u8d08\u6536\u5165"},{"page":1931,"x":2,"y":4,"ans":"\u4f59\u9e97\u5a9b"},{"page":1931,"x":2,"y":5,"ans":"J20******"},{"page":1931,"x":2,"y":6,"ans":"550"},{"page":1931,"x":2,"y":7,"ans":""},{"page":1931,"x":2,"y":9,"ans":"\u65b0\u5317\u5e02\u65b0\u838a\u5340"},{"page":1931,"x":3,"y":2,"ans":"100\/11\/07"},{"page":1931,"x":3,"y":3,"ans":"\u500b\u4eba\u6350\u8d08\u6536\u5165"},{"page":1931,"x":3,"y":4,"ans":"\u856d\u7f8e\u8ce2"},{"page":1931,"x":3,"y":5,"ans":"A22*******"},{"page":1931,"x":3,"y":6,"ans":"600"},{"page":1931,"x":3,"y":7,"ans":""},{"page":1931,"x":3,"y":9,"ans":"\u53f0\u5317\u5e02\u6587\u5c71\u5340"},{"page":1931,"x":4,"y":2,"ans":"100\/11\/07"},{"page":1931,"x":4,"y":3,"ans":"\u500b\u4eba\u6350\u8d08\u6536\u5165"},{"page":1931,"x":4,"y":4,"ans":"\u4e8e\u9577\u8277"},{"page":1931,"x":4,"y":5,"ans":"A22*******"},{"page":1931,"x":4,"y":6,"ans":"1,500"},{"page":1931,"x":4,"y":7,"ans":""},{"page":1931,"x":4,"y":9,"ans":""},{"page":1931,"x":5,"y":2,"ans":"100\/11\/07"},{"page":1931,"x":5,"y":3,"ans":"\u500b\u4eba\u6350\u8d08\u6536\u5165"},{"page":1931,"x":5,"y":4,"ans":"\u5ed6\u79b9\u4f69"},{"page":1931,"x":5,"y":5,"ans":"L22*******"},{"page":1931,"x":5,"y":6,"ans":"2,000"},{"page":1931,"x":5,"y":7,"ans":""},{"page":1931,"x":5,"y":9,"ans":"\u53f0\u4e2d\u5e02\u5317\u5c6f\u5340"},{"page":1931,"x":6,"y":2,"ans":"100\/11\/07"},{"page":1931,"x":6,"y":3,"ans":"\u500b\u4eba\u6350\u8d08\u6536\u5165"},{"page":1931,"x":6,"y":4,"ans":"\u5289\u667a\u73b2"},{"page":1931,"x":6,"y":5,"ans":"F22*******"},{"page":1931,"x":6,"y":6,"ans":"200"},{"page":1931,"x":6,"y":7,"ans":""},{"page":1931,"x":6,"y":9,"ans":"\u53f0\u5317\u5e02\u4e2d\u6b63\u5340"},{"page":1931,"x":7,"y":2,"ans":"100\/11\/07"},{"page":1931,"x":7,"y":3,"ans":"\u500b\u4eba\u6350\u8d08\u6536\u5165"},{"page":1931,"x":7,"y":4,"ans":"\u738b\u610f\u6f54"},{"page":1931,"x":7,"y":5,"ans":"F22*******"},{"page":1931,"x":7,"y":6,"ans":"900"},{"page":1931,"x":7,"y":7,"ans":""},{"page":1931,"x":7,"y":9,"ans":"\u82d7\u6817\u7e23\u7af9\u5357\u93ae"},{"page":1931,"x":8,"y":2,"ans":"100\/11\/07"},{"page":1931,"x":8,"y":3,"ans":"\u500b\u4eba\u6350\u8d08\u6536\u5165"},{"page":1931,"x":8,"y":4,"ans":"\u8449\u71d5\u5b0c"},{"page":1931,"x":8,"y":5,"ans":"C22*******"},{"page":1931,"x":8,"y":6,"ans":"300"},{"page":1931,"x":8,"y":7,"ans":""},{"page":1931,"x":8,"y":9,"ans":"\u57fa\u9686\u5e02\u4fe1\u7fa9\u5340"},{"page":1931,"x":9,"y":2,"ans":"100\/11\/07"},{"page":1931,"x":9,"y":3,"ans":"\u500b\u4eba\u6350\u8d08\u6536\u5165"},{"page":1931,"x":9,"y":4,"ans":"\u5442\u4fca\u8ce2"},{"page":1931,"x":9,"y":5,"ans":"S12*******"},{"page":1931,"x":9,"y":6,"ans":"200"},{"page":1931,"x":9,"y":7,"ans":""},{"page":1931,"x":9,"y":9,"ans":"\u6843\u5712\u7e23\u6843\u5712\u5e02"},{"page":1931,"x":10,"y":2,"ans":"100\/11\/07"},{"page":1931,"x":10,"y":3,"ans":"\u500b\u4eba\u6350\u8d08\u6536\u5165"},{"page":1931,"x":10,"y":4,"ans":"\u9867\u71d5\u502b"},{"page":1931,"x":10,"y":5,"ans":"B22*******"},{"page":1931,"x":10,"y":6,"ans":"1,000"},{"page":1931,"x":10,"y":7,"ans":""},{"page":1931,"x":10,"y":9,"ans":"\u53f0\u4e2d\u5e02\u897f\u5340\u9928"},{"page":1931,"x":11,"y":2,"ans":"100\/11\/07"},{"page":1931,"x":11,"y":3,"ans":"\u500b\u4eba\u6350\u8d08\u6536\u5165"},{"page":1931,"x":11,"y":4,"ans":"\u90ed\u7ad1\u9038"},{"page":1931,"x":11,"y":5,"ans":"R12*******"},{"page":1931,"x":11,"y":6,"ans":"300"},{"page":1931,"x":11,"y":7,"ans":""},{"page":1931,"x":11,"y":9,"ans":"\u6843\u5712\u7e23\u6843\u5712\u5e02"},{"page":1931,"x":12,"y":2,"ans":"100\/11\/07"},{"page":1931,"x":12,"y":3,"ans":"\u500b\u4eba\u6350\u8d08\u6536\u5165"},{"page":1931,"x":12,"y":4,"ans":"\u9ec3\u6dd1\u5a9b"},{"page":1931,"x":12,"y":5,"ans":"H22*******"},{"page":1931,"x":12,"y":6,"ans":"7,700"},{"page":1931,"x":12,"y":7,"ans":""},{"page":1931,"x":12,"y":9,"ans":"\u6843\u5712\u7e23\u5927\u6eaa\u93ae"},{"page":1931,"x":13,"y":2,"ans":"100\/11\/07"},{"page":1931,"x":13,"y":3,"ans":"\u500b\u4eba\u6350\u8d08\u6536\u5165"},{"page":1931,"x":13,"y":4,"ans":"\u738b\u8559\u829d"},{"page":1931,"x":13,"y":5,"ans":"A22*******"},{"page":1931,"x":13,"y":6,"ans":"1200"},{"page":1931,"x":13,"y":7,"ans":""},{"page":1931,"x":13,"y":9,"ans":"\u53f0\u5317\u5e02\u5927\u540c\u5340"},{"page":1931,"x":14,"y":2,"ans":"100\/11\/07"},{"page":1931,"x":14,"y":3,"ans":"\u500b\u4eba\u6350\u8d08\u6536\u5165"},{"page":1931,"x":14,"y":4,"ans":"\u9673\u8389\u8389"},{"page":1931,"x":14,"y":5,"ans":"H22*******"},{"page":1931,"x":14,"y":6,"ans":"300"},{"page":1931,"x":14,"y":7,"ans":""},{"page":1931,"x":14,"y":9,"ans":"\u82d7\u6817\u7e23\u7af9\u5357\u93ae"},{"page":1931,"x":15,"y":2,"ans":"101\/11\/07"},{"page":1931,"x":15,"y":3,"ans":"\u500b\u4eba\u6350\u8d08\u6536\u5165"},{"page":1931,"x":15,"y":4,"ans":"\u962e\u7389\u7426"},{"page":1931,"x":15,"y":5,"ans":"T22*******"},{"page":1931,"x":15,"y":6,"ans":"900"},{"page":1931,"x":15,"y":7,"ans":""},{"page":1931,"x":15,"y":9,"ans":"\u53f0\u5317\u5e02\u4fe1\u7fa9\u5340"},{"page":1931,"x":16,"y":2,"ans":"100\/11\/07"},{"page":1931,"x":16,"y":3,"ans":"\u500b\u4eba\u6350\u8d08\u6536\u5165"},{"page":1931,"x":16,"y":4,"ans":"\u6797\u60e0\u7389"},{"page":1931,"x":16,"y":5,"ans":"N22*******"},{"page":1931,"x":16,"y":6,"ans":"450"},{"page":1931,"x":16,"y":7,"ans":""},{"page":1931,"x":16,"y":9,"ans":"\u53f0\u4e2d\u5e02\u5357\u5340\u570b"},{"page":1931,"x":17,"y":2,"ans":"100\/11\/07"},{"page":1931,"x":17,"y":3,"ans":"\u500b\u4eba\u6350\u8d08\u6536\u5165"},{"page":1931,"x":17,"y":4,"ans":"\u5f35\u5cb8\u7915"},{"page":1931,"x":17,"y":5,"ans":"H12*******"},{"page":1931,"x":17,"y":6,"ans":"400"},{"page":1931,"x":17,"y":7,"ans":""},{"page":1931,"x":17,"y":9,"ans":"\u6843\u5712\u7e23\u9f9c\u5c71\u9109"},{"page":1931,"x":18,"y":2,"ans":"100\/11\/07"},{"page":1931,"x":18,"y":3,"ans":"\u500b\u4eba\u6350\u8d08\u6536\u5165"},{"page":1931,"x":18,"y":4,"ans":"\u6797\u975c\u7469"},{"page":1931,"x":18,"y":5,"ans":"F22*******"},{"page":1931,"x":18,"y":6,"ans":"900"},{"page":1931,"x":18,"y":7,"ans":""},{"page":1931,"x":18,"y":9,"ans":"\u53f0\u4e2d\u5e02\u897f\u5c6f\u5340"},{"page":1931,"x":19,"y":2,"ans":"100\/11\/07"},{"page":1931,"x":19,"y":3,"ans":"\u500b\u4eba\u6350\u8d08\u6536\u5165"},{"page":1931,"x":19,"y":4,"ans":"\u9ec3\u5c0f\u59d0"},{"page":1931,"x":19,"y":5,"ans":"R22*******"},{"page":1931,"x":19,"y":6,"ans":"1,200"},{"page":1931,"x":19,"y":7,"ans":""},{"page":1931,"x":19,"y":9,"ans":"\u53f0\u5357\u5e02\u65b0\u71df\u5340"},{"page":1931,"x":20,"y":2,"ans":"100\/11\/07"},{"page":1931,"x":20,"y":3,"ans":"\u500b\u4eba\u6350\u8d08\u6536\u5165"},{"page":1931,"x":20,"y":4,"ans":"\u856d\u7f8e\u9cf3"},{"page":1931,"x":20,"y":5,"ans":"H22*******"},{"page":1931,"x":20,"y":6,"ans":"300"},{"page":1931,"x":20,"y":7,"ans":""},{"page":1931,"x":20,"y":9,"ans":"\u65b0\u5317\u5e02\u4e2d\u548c\u5340"},{"page":1931,"x":21,"y":2,"ans":"100\/11\/07"},{"page":1931,"x":21,"y":3,"ans":"\u500b\u4eba\u6350\u8d08\u6536\u5165"},{"page":1931,"x":21,"y":4,"ans":"\u8a31\u529b\u4ec1"},{"page":1931,"x":21,"y":5,"ans":"S12*******"},{"page":1931,"x":21,"y":6,"ans":"300"},{"page":1931,"x":21,"y":7,"ans":""},{"page":1931,"x":21,"y":9,"ans":"\u9ad8\u96c4\u5e02\u9cf3\u5c71\u5340"}]