[{"page":2072,"x":2,"y":2,"ans":"101\/01\/12"},{"page":2072,"x":2,"y":3,"ans":"\u79df\u7528\u7af6\u9078\u8fa6\u4e8b\u8655\u652f\u51fa"},{"page":2072,"x":2,"y":4,"ans":"\u806f\u52d5\u884c\u92b7\u80a1\u4efd\u6709\u9650\u516c\u53f8"},{"page":2072,"x":2,"y":5,"ans":"24473458"},{"page":2072,"x":2,"y":6,"ans":""},{"page":2072,"x":2,"y":7,"ans":"104,059"},{"page":2072,"x":2,"y":9,"ans":"\u53f0\u5317\u5e02\u4fe1\u7fa9\u5340"},{"page":2072,"x":3,"y":2,"ans":"101\/01\/05"},{"page":2072,"x":3,"y":3,"ans":"\u79df\u7528\u7af6\u9078\u8fa6\u4e8b\u8655\u652f"},{"page":2072,"x":3,"y":4,"ans":""},{"page":2072,"x":3,"y":5,"ans":""},{"page":2072,"x":3,"y":6,"ans":""},{"page":2072,"x":3,"y":7,"ans":"5,250"},{"page":2072,"x":3,"y":9,"ans":""},{"page":2072,"x":4,"y":2,"ans":"11\/01\/04"},{"page":2072,"x":4,"y":3,"ans":"\u79df\u7528\u7af6\u9078\u8fa6\u4e8b\u8655\u652f\u51fa"},{"page":2072,"x":4,"y":4,"ans":"\u715c\u8ed2\u5ee3\u544a\u8a2d\u8a08\u793e"},{"page":2072,"x":4,"y":5,"ans":"87839406"},{"page":2072,"x":4,"y":6,"ans":""},{"page":2072,"x":4,"y":7,"ans":"164,035"},{"page":2072,"x":4,"y":9,"ans":"\u5357\u6295\u7e23\u8349\u5c6f\u93ae"},{"page":2072,"x":5,"y":2,"ans":"100\/12\/31"},{"page":2072,"x":5,"y":3,"ans":"\u79df\u7528\u7af6\u9078\u8fa6\u4e8b\u8655\u652f"},{"page":2072,"x":5,"y":4,"ans":"\u6234\u5b8f\u4e00"},{"page":2072,"x":5,"y":5,"ans":"N12*******"},{"page":2072,"x":5,"y":6,"ans":""},{"page":2072,"x":5,"y":7,"ans":"800,000"},{"page":2072,"x":5,"y":9,"ans":"\u81fa\u4e2d\u5e02\u5357\u5c6f\u5340"},{"page":2072,"x":6,"y":2,"ans":"100\/12\/31"},{"page":2072,"x":6,"y":3,"ans":"\u79df\u7528\u7af6\u9078\u8fa6\u4e8b\u8655\u652f\u51fa"},{"page":2072,"x":6,"y":4,"ans":"\u5b5f\u6176\u5bf0"},{"page":2072,"x":6,"y":5,"ans":"E22*******"},{"page":2072,"x":6,"y":6,"ans":""},{"page":2072,"x":6,"y":7,"ans":"200,000"},{"page":2072,"x":6,"y":9,"ans":"\u9ad8\u96c4\u5e02\u9cf3\u5c71\u5340"},{"page":2072,"x":7,"y":2,"ans":"100\/12\/31"},{"page":2072,"x":7,"y":3,"ans":"\u79df\u7528\u7af6\u9078\u8fa6\u4e8b\u8655\u652f"},{"page":2072,"x":7,"y":4,"ans":"\u5b5f\u6176\u5bf0"},{"page":2072,"x":7,"y":5,"ans":"E22\uff0a\uff0a\uff0a\uff0a\uff0a\uff0a\uff0a"},{"page":2072,"x":7,"y":6,"ans":""},{"page":2072,"x":7,"y":7,"ans":"200,000"},{"page":2072,"x":7,"y":9,"ans":"\u9ad8\u96c4\u5e02\u9cf3\u5c71\u5340"},{"page":2072,"x":8,"y":2,"ans":"100\/12\/31"},{"page":2072,"x":8,"y":3,"ans":"\u79df\u7528\u7af6\u9078\u8fa6\u4e8b\u8655\u652f"},{"page":2072,"x":8,"y":4,"ans":"\u5b5f\u6176\u5bf0"},{"page":2072,"x":8,"y":5,"ans":"E22*******"},{"page":2072,"x":8,"y":6,"ans":""},{"page":2072,"x":8,"y":7,"ans":"200000"},{"page":2072,"x":8,"y":9,"ans":"\u9ad8\u96c4\u5e02\u9cf3\u5c71\u5340"},{"page":2072,"x":9,"y":2,"ans":"100\/12\/31"},{"page":2072,"x":9,"y":3,"ans":"\u5ba3\u50b3\u652f\u51fa"},{"page":2072,"x":9,"y":4,"ans":"\u9802\u8c6a\u71df\u9020\u6709\u9650\u516c\u53f8"},{"page":2072,"x":9,"y":5,"ans":"79972957"},{"page":2072,"x":9,"y":6,"ans":""},{"page":2072,"x":9,"y":7,"ans":"25,000"},{"page":2072,"x":9,"y":9,"ans":""},{"page":2072,"x":10,"y":2,"ans":"100\/12\/30"},{"page":2072,"x":10,"y":3,"ans":"\u79df\u7528\u7af6\u9078\u8fa6\u4e8b\u8655\u652f\u51fa"},{"page":2072,"x":10,"y":4,"ans":"\u798f\u8339\u5be6\u696d\u6709\u9650\u516c\u53f8"},{"page":2072,"x":10,"y":5,"ans":"53638161"},{"page":2072,"x":10,"y":6,"ans":""},{"page":2072,"x":10,"y":7,"ans":"160,000"},{"page":2072,"x":10,"y":9,"ans":"\u5609\u7fa9\u7e23\u6c11\u96c4\u9109"},{"page":2072,"x":11,"y":2,"ans":"100\/12\/28"},{"page":2072,"x":11,"y":3,"ans":"\u79df\u7528\u7af6\u9078\u8fa6\u4e8b\u8655\u652f"},{"page":2072,"x":11,"y":4,"ans":"\u9673\u76c8\u9054"},{"page":2072,"x":11,"y":5,"ans":"Q10*******"},{"page":2072,"x":11,"y":6,"ans":""},{"page":2072,"x":11,"y":7,"ans":"375,000"},{"page":2072,"x":11,"y":9,"ans":"\u5609\u7fa9\u5e02\u516c\u660e\u8def"},{"page":2072,"x":12,"y":2,"ans":"100\/12\/25"},{"page":2072,"x":12,"y":3,"ans":"\u79df\u7528\u7af6\u9078\u8fa6\u4e8b\u8655\u652f"},{"page":2072,"x":12,"y":4,"ans":"\u7acb\u660c\u5efa\u6750\u884c"},{"page":2072,"x":12,"y":5,"ans":"09993515"},{"page":2072,"x":12,"y":6,"ans":""},{"page":2072,"x":12,"y":7,"ans":"8226"},{"page":2072,"x":12,"y":9,"ans":""},{"page":2072,"x":13,"y":2,"ans":"100\/12\/23"},{"page":2072,"x":13,"y":3,"ans":"\u79df\u7528\u7af6\u9078\u8fa6\u4e8b\u8655\u652f"},{"page":2072,"x":13,"y":4,"ans":"\u4e2d\u5f71\u80a1\u4efd\u6709\u9650\u516c\u53f8"},{"page":2072,"x":13,"y":5,"ans":"15047904"},{"page":2072,"x":13,"y":6,"ans":""},{"page":2072,"x":13,"y":7,"ans":"1633500"},{"page":2072,"x":13,"y":9,"ans":"\u53f0\u5317\u5e02\u516b\u5fb7\u8def"},{"page":2072,"x":14,"y":2,"ans":"100\/12\/22"},{"page":2072,"x":14,"y":3,"ans":"\u79df\u7528\u7af6\u9078\u8fa6\u4e8b\u8655\u652f"},{"page":2072,"x":14,"y":4,"ans":"\u5cb3\u68ee\u5de5\u7a0b\u884c"},{"page":2072,"x":14,"y":5,"ans":"25911032"},{"page":2072,"x":14,"y":6,"ans":""},{"page":2072,"x":14,"y":7,"ans":"25,000"},{"page":2072,"x":14,"y":9,"ans":""},{"page":2072,"x":15,"y":2,"ans":"100\/12\/20"},{"page":2072,"x":15,"y":3,"ans":"\u79df\u7528\u7af6\u9078\u8fa6\u4e8b\u8655\u652f"},{"page":2072,"x":15,"y":4,"ans":"\u5343\u5104\u5ba4\u5167\u88dd\u6f62\u884c"},{"page":2072,"x":15,"y":5,"ans":"92999276"},{"page":2072,"x":15,"y":6,"ans":""},{"page":2072,"x":15,"y":7,"ans":"35,000"},{"page":2072,"x":15,"y":9,"ans":"\u91d1\u9580\u7e23\u91d1\u6e56\u93ae"},{"page":2072,"x":16,"y":2,"ans":"100\/12\/16"},{"page":2072,"x":16,"y":3,"ans":"\u79df\u7528\u7af6\u9078\u8fa6\u4e8b\u8655\u652f"},{"page":2072,"x":16,"y":4,"ans":"\u9ec3\u7404\u6d93"},{"page":2072,"x":16,"y":5,"ans":"A22\uff0a\uff0a\uff0a\uff0a\uff0a\uff0a\uff0a"},{"page":2072,"x":16,"y":6,"ans":""},{"page":2072,"x":16,"y":7,"ans":"90,000"},{"page":2072,"x":16,"y":9,"ans":"\u53f0\u5357\u5e02\u5b89\u5e73\u5340"},{"page":2072,"x":17,"y":2,"ans":"100\/12\/16"},{"page":2072,"x":17,"y":3,"ans":"\u79df\u7528\u7af6\u9078\u8fa6\u4e8b\u8655\u652f\u51fa"},{"page":2072,"x":17,"y":4,"ans":"\u7fc1\u660e\u8000"},{"page":2072,"x":17,"y":5,"ans":"Q12*******"},{"page":2072,"x":17,"y":6,"ans":""},{"page":2072,"x":17,"y":7,"ans":"100,000"},{"page":2072,"x":17,"y":9,"ans":"\u9ad8\u96c4\u5e02\u9f13\u5c71\u5340"},{"page":2072,"x":18,"y":2,"ans":"100\/12\/10"},{"page":2072,"x":18,"y":3,"ans":"\u79df\u7528\u7af6\u9078\u8fa6\u4e8b\u8655\u652f"},{"page":2072,"x":18,"y":4,"ans":"\u5b8f\u798f\u751f\u5316\u79d1\u6280\u6709\u9650\u516c\u53f8"},{"page":2072,"x":18,"y":5,"ans":"28285597"},{"page":2072,"x":18,"y":6,"ans":""},{"page":2072,"x":18,"y":7,"ans":"300,000"},{"page":2072,"x":18,"y":9,"ans":"\u9ad8\u96c4\u5e02\u65b0\u8208\u5340"},{"page":2072,"x":19,"y":2,"ans":"100\/12\/10"},{"page":2072,"x":19,"y":3,"ans":"\u79df\u7528\u7af6\u9078\u8fa6\u4e8b\u8655\u652f"},{"page":2072,"x":19,"y":4,"ans":"\u627f\u6fa4\u5de5\u7a0b\u6709\u9650\u516c\u53f8"},{"page":2072,"x":19,"y":5,"ans":"27209191"},{"page":2072,"x":19,"y":6,"ans":""},{"page":2072,"x":19,"y":7,"ans":"9,209"},{"page":2072,"x":19,"y":9,"ans":""},{"page":2072,"x":20,"y":2,"ans":"100\/12\/10"},{"page":2072,"x":20,"y":3,"ans":"\u516c\u5171\u95dc\u4fc2\u8cbb\u7528\u652f\u51fa"},{"page":2072,"x":20,"y":4,"ans":"\u84ee\u6b23\u79d1\u6280\u80a1\u4efd\u6709\u9650\u516c\u53f8"},{"page":2072,"x":20,"y":5,"ans":"28245"},{"page":2072,"x":20,"y":6,"ans":""},{"page":2072,"x":20,"y":7,"ans":"28,245"},{"page":2072,"x":20,"y":9,"ans":""},{"page":2072,"x":21,"y":2,"ans":"100\/12\/10"},{"page":2072,"x":21,"y":3,"ans":"\u79df\u7528\u7af6\u9078\u8fa6\u4e8b\u8655\u652f"},{"page":2072,"x":21,"y":4,"ans":"\u5409\u8c50\u6c34\u96fb\u884c"},{"page":2072,"x":21,"y":5,"ans":"99400099"},{"page":2072,"x":21,"y":6,"ans":""},{"page":2072,"x":21,"y":7,"ans":"31,080"},{"page":2072,"x":21,"y":9,"ans":"\u9ad8\u96c4\u5e02\u524d\u93ae\u5340"}]