[{"page":2105,"x":2,"y":2,"ans":"101\/02\/09"},{"page":2105,"x":2,"y":3,"ans":"\u4eba\u4e8b\u8cbb\u7528\u652f\u51fa"},{"page":2105,"x":2,"y":4,"ans":"\u6d2a\u9577\u76ca"},{"page":2105,"x":2,"y":5,"ans":"M10*******"},{"page":2105,"x":2,"y":6,"ans":""},{"page":2105,"x":2,"y":7,"ans":"2,000"},{"page":2105,"x":2,"y":9,"ans":"\u5357\u6295\u7e23\u8349\u5c6f\u93ae"},{"page":2105,"x":3,"y":2,"ans":"101\/02\/09"},{"page":2105,"x":3,"y":3,"ans":"\u4eba\u4e8b\u8cbb\u7528\u652f\u51fa"},{"page":2105,"x":3,"y":4,"ans":"\u8a31\u5e7c\u6b23"},{"page":2105,"x":3,"y":5,"ans":"S22*******"},{"page":2105,"x":3,"y":6,"ans":""},{"page":2105,"x":3,"y":7,"ans":"2000"},{"page":2105,"x":3,"y":9,"ans":"\u9ad8\u96c4\u5e02\u6a4b\u982d\u5340"},{"page":2105,"x":4,"y":2,"ans":"101\/02\/09"},{"page":2105,"x":4,"y":3,"ans":"\u4eba\u4e8b\u8cbb\u7528\u652f\u51fa"},{"page":2105,"x":4,"y":4,"ans":"\u674e\u5fc3\u4ec1"},{"page":2105,"x":4,"y":5,"ans":"K12*******"},{"page":2105,"x":4,"y":6,"ans":""},{"page":2105,"x":4,"y":7,"ans":"2,000"},{"page":2105,"x":4,"y":9,"ans":"\u82d7\u6817\u7e23\u982d\u4efd\u93ae"},{"page":2105,"x":5,"y":2,"ans":"101\/02\/09"},{"page":2105,"x":5,"y":3,"ans":"\u4eba\u4e8b\u8cbb\u7528\u652f\u51fa"},{"page":2105,"x":5,"y":4,"ans":"\u694a\u8d85\u51f1"},{"page":2105,"x":5,"y":5,"ans":"A12*******"},{"page":2105,"x":5,"y":6,"ans":""},{"page":2105,"x":5,"y":7,"ans":"2,000"},{"page":2105,"x":5,"y":9,"ans":"\u53f0\u5317\u5e02\u4e2d\u5c71\u5340"},{"page":2105,"x":6,"y":2,"ans":"101\/02\/09"},{"page":2105,"x":6,"y":3,"ans":"\u4eba\u4e8b\u8cbb\u7528\u652f\u51fa"},{"page":2105,"x":6,"y":4,"ans":"\u5433\u79c0\u771f"},{"page":2105,"x":6,"y":5,"ans":"M20*******"},{"page":2105,"x":6,"y":6,"ans":""},{"page":2105,"x":6,"y":7,"ans":"25,000"},{"page":2105,"x":6,"y":9,"ans":"\u5357\u6295\u5e02\u4e09\u548c\u91cc"},{"page":2105,"x":7,"y":2,"ans":"101\/02\/09"},{"page":2105,"x":7,"y":3,"ans":"\u4eba\u4e8b\u8cbb\u7528\u652f\u51fa"},{"page":2105,"x":7,"y":4,"ans":"\u8a79\u91d1\u58a9"},{"page":2105,"x":7,"y":5,"ans":"M12\uff0a\uff0a\uff0a\uff0a\uff0a\uff0a\uff0a"},{"page":2105,"x":7,"y":6,"ans":""},{"page":2105,"x":7,"y":7,"ans":"25000"},{"page":2105,"x":7,"y":9,"ans":"\u5357\u6295\u7e23\u8349\u5c6f\u93ae"},{"page":2105,"x":8,"y":2,"ans":"101\/02\/09"},{"page":2105,"x":8,"y":3,"ans":"\u4eba\u4e8b\u8cbb\u7528\u652f\u51fa"},{"page":2105,"x":8,"y":4,"ans":"\u8b1d\u671d\u5b87"},{"page":2105,"x":8,"y":5,"ans":"M10*******"},{"page":2105,"x":8,"y":6,"ans":""},{"page":2105,"x":8,"y":7,"ans":"12\uff0c500"},{"page":2105,"x":8,"y":9,"ans":"\u5357\u6295\u5e02\u516b\u5366\u8def"},{"page":2105,"x":9,"y":2,"ans":"101\/02\/09"},{"page":2105,"x":9,"y":3,"ans":"\u4eba\u4e8b\u8cbb\u7528\u652f\u51fa"},{"page":2105,"x":9,"y":4,"ans":"\u6d2a\u6dd1\u537f"},{"page":2105,"x":9,"y":5,"ans":"M22*******"},{"page":2105,"x":9,"y":6,"ans":""},{"page":2105,"x":9,"y":7,"ans":"12,500"},{"page":2105,"x":9,"y":9,"ans":"\u5357\u6295\u5e02\u8208\u91cc\u81ea"},{"page":2105,"x":10,"y":2,"ans":"101\/02\/09"},{"page":2105,"x":10,"y":3,"ans":"\u4eba\u4e8b\u8cbb\u7528\u652f\u51fa"},{"page":2105,"x":10,"y":4,"ans":"\u694a\u6dd1\u96f2"},{"page":2105,"x":10,"y":5,"ans":"M22*******"},{"page":2105,"x":10,"y":6,"ans":""},{"page":2105,"x":10,"y":7,"ans":"73,760"},{"page":2105,"x":10,"y":9,"ans":"\u5357\u6295\u7e23\u7af9\u5c71\u93ae"},{"page":2105,"x":11,"y":2,"ans":"101\/02\/09"},{"page":2105,"x":11,"y":3,"ans":"\u4eba\u4e8b\u8cbb\u7528\u652f\u51fa"},{"page":2105,"x":11,"y":4,"ans":"\u5289\u6b23\u7a4e"},{"page":2105,"x":11,"y":5,"ans":"m22"},{"page":2105,"x":11,"y":6,"ans":""},{"page":2105,"x":11,"y":7,"ans":"3,000"},{"page":2105,"x":11,"y":9,"ans":"\u5357\u6295\u7e23\u7af9\u5c71\u93ae"},{"page":2105,"x":12,"y":2,"ans":"101\/02\/09"},{"page":2105,"x":12,"y":3,"ans":"\u4eba\u4e8b\u8cbb\u7528\u652f\u51fa"},{"page":2105,"x":12,"y":4,"ans":"\u8521\u6dd1\u84ee"},{"page":2105,"x":12,"y":5,"ans":"L22*******"},{"page":2105,"x":12,"y":6,"ans":""},{"page":2105,"x":12,"y":7,"ans":"2,000"},{"page":2105,"x":12,"y":9,"ans":"\u5357\u6295\u7e23\u7af9\u5c71\u93ae"},{"page":2105,"x":13,"y":2,"ans":"101\/02\/09"},{"page":2105,"x":13,"y":3,"ans":"\u4eba\u4e8b\u8cbb\u7528\u652f\u51fa"},{"page":2105,"x":13,"y":4,"ans":"\u5ed6\u6dd1\u83ef"},{"page":2105,"x":13,"y":5,"ans":"M22*******"},{"page":2105,"x":13,"y":6,"ans":""},{"page":2105,"x":13,"y":7,"ans":"2000"},{"page":2105,"x":13,"y":9,"ans":"\u5357\u6295\u7e23\u8349\u5c6f\u93ae"},{"page":2105,"x":14,"y":2,"ans":"101\/02\/09"},{"page":2105,"x":14,"y":3,"ans":"\u4eba\u4e8b\u8cbb\u7528\u652f\u51fa"},{"page":2105,"x":14,"y":4,"ans":"\u53e4\u7f8e\u73cd"},{"page":2105,"x":14,"y":5,"ans":"M22*******"},{"page":2105,"x":14,"y":6,"ans":""},{"page":2105,"x":14,"y":7,"ans":"2,000"},{"page":2105,"x":14,"y":9,"ans":"\u5357\u6295\u7e23\u8349\u5c6f\u93ae"},{"page":2105,"x":15,"y":2,"ans":"101\/02\/09"},{"page":2105,"x":15,"y":3,"ans":"\u4eba\u4e8b\u8cbb\u7528\u652f\u51fa"},{"page":2105,"x":15,"y":4,"ans":"\u90ed\u963f\u7d20"},{"page":2105,"x":15,"y":5,"ans":"M22*******"},{"page":2105,"x":15,"y":6,"ans":""},{"page":2105,"x":15,"y":7,"ans":"2,000"},{"page":2105,"x":15,"y":9,"ans":"\u5357\u6295\u7e23\u8349\u5c6f\u93ae"},{"page":2105,"x":16,"y":2,"ans":"101\/02\/09"},{"page":2105,"x":16,"y":3,"ans":"\u4eba\u4e8b\u8cbb\u7528\u652f\u51fa"},{"page":2105,"x":16,"y":4,"ans":"\u838a\u7d20\u5a1f"},{"page":2105,"x":16,"y":5,"ans":"M22*******"},{"page":2105,"x":16,"y":6,"ans":""},{"page":2105,"x":16,"y":7,"ans":"2000"},{"page":2105,"x":16,"y":9,"ans":"\u5357\u6295\u7e23\u8349\u5c6f\u93ae"},{"page":2105,"x":17,"y":2,"ans":"101\/02\/09"},{"page":2105,"x":17,"y":3,"ans":"\u4eba\u4e8b\u8cbb\u7528\u652f\u51fa"},{"page":2105,"x":17,"y":4,"ans":"\u9673\u9326\u6893"},{"page":2105,"x":17,"y":5,"ans":"M22*******"},{"page":2105,"x":17,"y":6,"ans":""},{"page":2105,"x":17,"y":7,"ans":"2,000"},{"page":2105,"x":17,"y":9,"ans":"\u5357\u6295\u7e23\u8349\u5c6f\u93ae"},{"page":2105,"x":18,"y":2,"ans":"101\/02\/09"},{"page":2105,"x":18,"y":3,"ans":"\u4eba\u4e8b\u8cbb\u7528\u652f\u51fa"},{"page":2105,"x":18,"y":4,"ans":"\u6797\u6625\u679d"},{"page":2105,"x":18,"y":5,"ans":"M20*******"},{"page":2105,"x":18,"y":6,"ans":""},{"page":2105,"x":18,"y":7,"ans":"7,000"},{"page":2105,"x":18,"y":9,"ans":"\u5357\u6295\u7e23\u8349\u5c6f\u93ae"},{"page":2105,"x":19,"y":2,"ans":"101\/02\/09"},{"page":2105,"x":19,"y":3,"ans":"\u4eba\u4e8b\u8cbb\u7528\u652f\u51fa"},{"page":2105,"x":19,"y":4,"ans":"\u9127\u745e\u52f3"},{"page":2105,"x":19,"y":5,"ans":"M12*******"},{"page":2105,"x":19,"y":6,"ans":""},{"page":2105,"x":19,"y":7,"ans":"2000"},{"page":2105,"x":19,"y":9,"ans":"\u5357\u6295\u7e23\u8349\u5c6f\u93ae"},{"page":2105,"x":20,"y":2,"ans":"101\/02\/09"},{"page":2105,"x":20,"y":3,"ans":""},{"page":2105,"x":20,"y":4,"ans":"\u6d2a\u5411\u7fa9"},{"page":2105,"x":20,"y":5,"ans":"12"},{"page":2105,"x":20,"y":6,"ans":""},{"page":2105,"x":20,"y":7,"ans":"2,000"},{"page":2105,"x":20,"y":9,"ans":"\u5357\u6295\u7e23\u8349\u5c6f\u93ae"},{"page":2105,"x":21,"y":2,"ans":"101\/02\/09"},{"page":2105,"x":21,"y":3,"ans":"\u4eba\u4e8b\u8cbb\u7528\u652f\u51fa"},{"page":2105,"x":21,"y":4,"ans":"\u6c5f\u4e0a\u842c"},{"page":2105,"x":21,"y":5,"ans":"M10*******"},{"page":2105,"x":21,"y":6,"ans":""},{"page":2105,"x":21,"y":7,"ans":"2,000"},{"page":2105,"x":21,"y":9,"ans":"\u5357\u6295\u7e23\u8349\u5c6f\u93ae"}]