[{"page":2230,"x":2,"y":2,"ans":"101\/01\/14"},{"page":2230,"x":2,"y":3,"ans":"\u4ea4\u901a\u65c5\u904b\u652f\u51fa"},{"page":2230,"x":2,"y":4,"ans":"\u5168\u5bb6\u4fbf\u5229\u5546\u5e97\u80a1\u4efd\u6709\u9650\u516c\u53f8"},{"page":2230,"x":2,"y":5,"ans":""},{"page":2230,"x":2,"y":6,"ans":""},{"page":2230,"x":2,"y":7,"ans":"211"},{"page":2230,"x":2,"y":9,"ans":""},{"page":2230,"x":3,"y":2,"ans":"101\/01\/14"},{"page":2230,"x":3,"y":3,"ans":"\u4ea4\u901a\u65c5\u904b\u652f\u51fa"},{"page":2230,"x":3,"y":4,"ans":"\u7d71\u4e00\u8d85\u5546\u80a1\u4efd\u6709\u9650\u516c\u53f8"},{"page":2230,"x":3,"y":5,"ans":""},{"page":2230,"x":3,"y":6,"ans":""},{"page":2230,"x":3,"y":7,"ans":"89"},{"page":2230,"x":3,"y":9,"ans":""},{"page":2230,"x":4,"y":2,"ans":"101\/01\/14"},{"page":2230,"x":4,"y":3,"ans":"\u4ea4\u901a\u65c5\u904b\u652f\u51fa"},{"page":2230,"x":4,"y":4,"ans":"\u9f8d\u904b\u4ea4\u901a\u6709\u9650\u516c\u53f8"},{"page":2230,"x":4,"y":5,"ans":""},{"page":2230,"x":4,"y":6,"ans":""},{"page":2230,"x":4,"y":7,"ans":"120"},{"page":2230,"x":4,"y":9,"ans":""},{"page":2230,"x":5,"y":2,"ans":"101\/01\/14"},{"page":2230,"x":5,"y":3,"ans":"\u4ea4\u901a\u65c5\u904b\u652f\u51fa"},{"page":2230,"x":5,"y":4,"ans":"\u674e\u6e05\u7965"},{"page":2230,"x":5,"y":5,"ans":""},{"page":2230,"x":5,"y":6,"ans":""},{"page":2230,"x":5,"y":7,"ans":"150"},{"page":2230,"x":5,"y":9,"ans":""},{"page":2230,"x":6,"y":2,"ans":"101\/01\/14"},{"page":2230,"x":6,"y":3,"ans":"\u4ea4\u901a\u65c5\u904b\u652f\u51fa"},{"page":2230,"x":6,"y":4,"ans":"\u53f0\u7063\u9435\u8def\u5c40"},{"page":2230,"x":6,"y":5,"ans":""},{"page":2230,"x":6,"y":6,"ans":""},{"page":2230,"x":6,"y":7,"ans":"30"},{"page":2230,"x":6,"y":9,"ans":""},{"page":2230,"x":7,"y":2,"ans":"101\/01\/14"},{"page":2230,"x":7,"y":3,"ans":"\u4ea4\u901a\u65c5\u8cbb\u652f\u51fa"},{"page":2230,"x":7,"y":4,"ans":"\u6676\u54c1\u8336\u884c"},{"page":2230,"x":7,"y":5,"ans":""},{"page":2230,"x":7,"y":6,"ans":""},{"page":2230,"x":7,"y":7,"ans":"135"},{"page":2230,"x":7,"y":9,"ans":""},{"page":2230,"x":8,"y":2,"ans":"101\/01\/14"},{"page":2230,"x":8,"y":3,"ans":"\u4ea4\u901a\u65c5\u904b\u652f\u51fa"},{"page":2230,"x":8,"y":4,"ans":"\u6771\u5712\u5927\u98ef\u5e97\u6709\u9650\u516c\u53f8"},{"page":2230,"x":8,"y":5,"ans":""},{"page":2230,"x":8,"y":6,"ans":""},{"page":2230,"x":8,"y":7,"ans":"1,200"},{"page":2230,"x":8,"y":9,"ans":""},{"page":2230,"x":9,"y":2,"ans":"101\/01\/14"},{"page":2230,"x":9,"y":3,"ans":"\u4ea4\u901a\u65c5\u904b\u652f\u51fa"},{"page":2230,"x":9,"y":4,"ans":"\u4e09\u654f\u8a08\u7a0b\u8eca\u884c"},{"page":2230,"x":9,"y":5,"ans":"\u8ca1\u7522"},{"page":2230,"x":9,"y":6,"ans":""},{"page":2230,"x":9,"y":7,"ans":"500"},{"page":2230,"x":9,"y":9,"ans":""},{"page":2230,"x":10,"y":2,"ans":"101\/01\/14"},{"page":2230,"x":10,"y":3,"ans":"\u4ea4\u901a\u65c5\u904b\u652f\u51fa"},{"page":2230,"x":10,"y":4,"ans":"\u8449\u4f73\u5bf6"},{"page":2230,"x":10,"y":5,"ans":""},{"page":2230,"x":10,"y":6,"ans":""},{"page":2230,"x":10,"y":7,"ans":"125"},{"page":2230,"x":10,"y":9,"ans":""},{"page":2230,"x":11,"y":2,"ans":"101\/01\/14"},{"page":2230,"x":11,"y":3,"ans":"\u4ea4\u901a\u65c5\u904b\u652f\u51fa"},{"page":2230,"x":11,"y":4,"ans":"\u53f0\u7063\u9ad8\u9435"},{"page":2230,"x":11,"y":5,"ans":""},{"page":2230,"x":11,"y":6,"ans":""},{"page":2230,"x":11,"y":7,"ans":"700"},{"page":2230,"x":11,"y":9,"ans":""},{"page":2230,"x":12,"y":2,"ans":"101\/01\/14"},{"page":2230,"x":12,"y":3,"ans":"\u4ea4\u901a\u65c5\u904b\u652f\u51fa"},{"page":2230,"x":12,"y":4,"ans":"\u4e9e\u7c73\u98a8\u5473\u5c0f\u5403\u5e97"},{"page":2230,"x":12,"y":5,"ans":""},{"page":2230,"x":12,"y":6,"ans":""},{"page":2230,"x":12,"y":7,"ans":"300"},{"page":2230,"x":12,"y":9,"ans":""},{"page":2230,"x":13,"y":2,"ans":"101\/01\/14"},{"page":2230,"x":13,"y":3,"ans":"\u4ea4\u901a\u65c5\u904b\u652f\u51fa"},{"page":2230,"x":13,"y":4,"ans":"\u6cdb\u4e9e\u885b\u661f"},{"page":2230,"x":13,"y":5,"ans":""},{"page":2230,"x":13,"y":6,"ans":""},{"page":2230,"x":13,"y":7,"ans":"75"},{"page":2230,"x":13,"y":9,"ans":""},{"page":2230,"x":14,"y":2,"ans":"101\/01\/14"},{"page":2230,"x":14,"y":3,"ans":"\u4ea4\u901a\u65c5\u904b\u652f\u51fa"},{"page":2230,"x":14,"y":4,"ans":"\u570b\u4ec1\u4ea4\u901a\u95dc\u4fc2\u4f01\u696d\u6709\u9650\u516c\u53f8"},{"page":2230,"x":14,"y":5,"ans":""},{"page":2230,"x":14,"y":6,"ans":""},{"page":2230,"x":14,"y":7,"ans":"220"},{"page":2230,"x":14,"y":9,"ans":""},{"page":2230,"x":15,"y":2,"ans":"101\/01\/14"},{"page":2230,"x":15,"y":3,"ans":"\u4ea4\u901a\u65c5\u904b\u652f\u51fa"},{"page":2230,"x":15,"y":4,"ans":"\u66f9\u8070\u8f1d"},{"page":2230,"x":15,"y":5,"ans":""},{"page":2230,"x":15,"y":6,"ans":""},{"page":2230,"x":15,"y":7,"ans":"345"},{"page":2230,"x":15,"y":9,"ans":""},{"page":2230,"x":16,"y":2,"ans":"101\/01\/14"},{"page":2230,"x":16,"y":3,"ans":"\u4ea4\u901a\u65c5\u904b\u652f\u51fa"},{"page":2230,"x":16,"y":4,"ans":"\u540d\u8aa0\u5c0f\u5403\u5e97"},{"page":2230,"x":16,"y":5,"ans":"\u9662"},{"page":2230,"x":16,"y":6,"ans":""},{"page":2230,"x":16,"y":7,"ans":"150"},{"page":2230,"x":16,"y":9,"ans":""},{"page":2230,"x":17,"y":2,"ans":"101\/01\/14"},{"page":2230,"x":17,"y":3,"ans":"\u4ea4\u901a\u65c5\u904b\u652f\u51fa"},{"page":2230,"x":17,"y":4,"ans":"\u53f0\u7063\u5927\u8eca\u968a\u7b49"},{"page":2230,"x":17,"y":5,"ans":""},{"page":2230,"x":17,"y":6,"ans":""},{"page":2230,"x":17,"y":7,"ans":"480"},{"page":2230,"x":17,"y":9,"ans":""},{"page":2230,"x":18,"y":2,"ans":"101\/01\/14"},{"page":2230,"x":18,"y":3,"ans":"\u4ea4\u901a\u65c5\u904b\u652f\u51fa"},{"page":2230,"x":18,"y":4,"ans":"\u4e0a\u6e6f\u934b\u71d2\u9eb5\u5c08\u8ce3\u5e97"},{"page":2230,"x":18,"y":5,"ans":""},{"page":2230,"x":18,"y":6,"ans":""},{"page":2230,"x":18,"y":7,"ans":"150"},{"page":2230,"x":18,"y":9,"ans":""},{"page":2230,"x":19,"y":2,"ans":"101\/01\/14"},{"page":2230,"x":19,"y":3,"ans":"\u4ea4\u901a\u65c5\u904b\u652f\u51fa"},{"page":2230,"x":19,"y":4,"ans":"\u4e2d\u83ef\u885b\u661f\u53f0\u5357\u8eca\u968a"},{"page":2230,"x":19,"y":5,"ans":""},{"page":2230,"x":19,"y":6,"ans":""},{"page":2230,"x":19,"y":7,"ans":"570"},{"page":2230,"x":19,"y":9,"ans":""},{"page":2230,"x":20,"y":2,"ans":"101\/01\/14"},{"page":2230,"x":20,"y":3,"ans":"\u4ea4\u901a\u65c5\u904b\u652f\u51fa"},{"page":2230,"x":20,"y":4,"ans":"\u4ec1\u570b\u4ea4\u901a\u95dc\u4fc2\u4f01\u696d\u6709\u9650\u516c\u53f8"},{"page":2230,"x":20,"y":5,"ans":""},{"page":2230,"x":20,"y":6,"ans":""},{"page":2230,"x":20,"y":7,"ans":"220"},{"page":2230,"x":20,"y":9,"ans":""},{"page":2230,"x":21,"y":2,"ans":"101\/01\/14"},{"page":2230,"x":21,"y":3,"ans":"\u4ea4\u901a\u65c5\u904b\u652f\u51fa"},{"page":2230,"x":21,"y":4,"ans":"\u5468\u7fa9\u5fe0"},{"page":2230,"x":21,"y":5,"ans":""},{"page":2230,"x":21,"y":6,"ans":""},{"page":2230,"x":21,"y":7,"ans":"125"},{"page":2230,"x":21,"y":9,"ans":""}]