[{"page":2376,"x":2,"y":2,"ans":"100\/12\/09"},{"page":2376,"x":2,"y":3,"ans":"\u500b\u4eba\u6350\u8d08\u6536\u5165"},{"page":2376,"x":2,"y":4,"ans":"\u90b1\u9e97\u82b3"},{"page":2376,"x":2,"y":5,"ans":"N20*******"},{"page":2376,"x":2,"y":6,"ans":"100,000"},{"page":2376,"x":2,"y":7,"ans":""},{"page":2376,"x":2,"y":9,"ans":"\u53f0\u4e2d\u5e02\u897f\u5c6f\u5340"},{"page":2376,"x":3,"y":2,"ans":"100\/12\/09"},{"page":2376,"x":3,"y":3,"ans":"\u500b\u4eba\u6350\u8d08\u6536\u5165"},{"page":2376,"x":3,"y":4,"ans":"\u8521\u570b\u6d32"},{"page":2376,"x":3,"y":5,"ans":"N12*******"},{"page":2376,"x":3,"y":6,"ans":"100,000"},{"page":2376,"x":3,"y":7,"ans":""},{"page":2376,"x":3,"y":9,"ans":"\u81fa\u4e2d\u5e02\u5317\u5340\u6de1"},{"page":2376,"x":4,"y":2,"ans":"100\/12\/05"},{"page":2376,"x":4,"y":3,"ans":"\u500b\u4eba\u6350\u8d08\u6536\u5165"},{"page":2376,"x":4,"y":4,"ans":"\u6797\u4e16\u9298"},{"page":2376,"x":4,"y":5,"ans":"M12\uff0a\uff0a\uff0a\uff0a\uff0a\uff0a\uff0a"},{"page":2376,"x":4,"y":6,"ans":"100,000"},{"page":2376,"x":4,"y":7,"ans":""},{"page":2376,"x":4,"y":9,"ans":"\u5f70\u5316\u7e23\u79c0\u6c34\u9109"},{"page":2376,"x":5,"y":2,"ans":"100\/12\/05"},{"page":2376,"x":5,"y":3,"ans":"\u500b\u4eba\u6350\u8d08\u6536\u5165"},{"page":2376,"x":5,"y":4,"ans":"\u67ef\u6c5f\u6d77"},{"page":2376,"x":5,"y":5,"ans":""},{"page":2376,"x":5,"y":6,"ans":""},{"page":2376,"x":5,"y":7,"ans":""},{"page":2376,"x":5,"y":9,"ans":"\u5f70\u5316\u7e23\u4f38\u6e2f\u9109"},{"page":2376,"x":6,"y":2,"ans":"100\/12\/05"},{"page":2376,"x":6,"y":3,"ans":"\u500b\u4eba\u6350\u8d08\u6536\u5165"},{"page":2376,"x":6,"y":4,"ans":"\u674e\u5efa\u5c45"},{"page":2376,"x":6,"y":5,"ans":"N12*******"},{"page":2376,"x":6,"y":6,"ans":"5,000"},{"page":2376,"x":6,"y":7,"ans":""},{"page":2376,"x":6,"y":9,"ans":"\u5f70\u5316\u7e23\u9e7f\u6e2f\u93ae"},{"page":2376,"x":7,"y":2,"ans":"100\/12\/05"},{"page":2376,"x":7,"y":3,"ans":"\u500b\u4eba\u6350\u8d08\u6536\u5165"},{"page":2376,"x":7,"y":4,"ans":"\u90ed\u6e05\u826f"},{"page":2376,"x":7,"y":5,"ans":"N10*********"},{"page":2376,"x":7,"y":6,"ans":"10,000"},{"page":2376,"x":7,"y":7,"ans":""},{"page":2376,"x":7,"y":9,"ans":"\u5f70\u5316\u7e23\u9e7f\u6e2f\u93ae"},{"page":2376,"x":8,"y":2,"ans":"100\/12\/05"},{"page":2376,"x":8,"y":3,"ans":"\u500b\u4eba\u6350\u8d08\u6536\u5165"},{"page":2376,"x":8,"y":4,"ans":"\u4f55\u4efb\u5cf0"},{"page":2376,"x":8,"y":5,"ans":"N10*******"},{"page":2376,"x":8,"y":6,"ans":"6,600"},{"page":2376,"x":8,"y":7,"ans":""},{"page":2376,"x":8,"y":9,"ans":"\u5f70\u5316\u7e23\u54e1\u6797\u93ae"},{"page":2376,"x":9,"y":2,"ans":"100\/12\/05"},{"page":2376,"x":9,"y":3,"ans":"\u500b\u4eba\u6350\u8d08\u6536\u5165"},{"page":2376,"x":9,"y":4,"ans":"\u8b1d\u4fdd\u7f85"},{"page":2376,"x":9,"y":5,"ans":"N12*******"},{"page":2376,"x":9,"y":6,"ans":"100,000"},{"page":2376,"x":9,"y":7,"ans":""},{"page":2376,"x":9,"y":9,"ans":"\u5f70\u5316\u7e23\u9e7f\u6e2f\u93ae"},{"page":2376,"x":10,"y":2,"ans":"100\/12\/05"},{"page":2376,"x":10,"y":3,"ans":"\u500b\u4eba\u6350\u8d08\u6536\u5165"},{"page":2376,"x":10,"y":4,"ans":"\u65bd\u4fca\u826f"},{"page":2376,"x":10,"y":5,"ans":"\u500b\u4eba\u6350\u8d08\u6536\u5165"},{"page":2376,"x":10,"y":6,"ans":"20,000"},{"page":2376,"x":10,"y":7,"ans":""},{"page":2376,"x":10,"y":9,"ans":"\u5f70\u5316\u7e23\u9e7f\u6e2f\u93ae"},{"page":2376,"x":11,"y":2,"ans":"100\/12\/02"},{"page":2376,"x":11,"y":3,"ans":"\u500b\u4eba\u6350\u8d08\u6536\u5165"},{"page":2376,"x":11,"y":4,"ans":"\u8521\u570b\u7433"},{"page":2376,"x":11,"y":5,"ans":"N12*******"},{"page":2376,"x":11,"y":6,"ans":"10000"},{"page":2376,"x":11,"y":7,"ans":""},{"page":2376,"x":11,"y":9,"ans":"\u5f70\u5316\u7e23\u9e7f\u6e2f\u93ae"},{"page":2376,"x":12,"y":2,"ans":"100\/12\/02"},{"page":2376,"x":12,"y":3,"ans":"\u500b\u4eba\u6350\u8d08\u6536\u5165"},{"page":2376,"x":12,"y":4,"ans":"\u7fc1\u6625\u6dd1"},{"page":2376,"x":12,"y":5,"ans":"N22*******"},{"page":2376,"x":12,"y":6,"ans":"100,000"},{"page":2376,"x":12,"y":7,"ans":""},{"page":2376,"x":12,"y":9,"ans":"\u5f70\u5316\u7e23\u793e\u982d\u9109"},{"page":2376,"x":13,"y":2,"ans":"100\/12\/02"},{"page":2376,"x":13,"y":3,"ans":"\u500b\u4eba\u6350\u8d08\u6536\u5165"},{"page":2376,"x":13,"y":4,"ans":"\u856d\u5289\u91d1\u82f1"},{"page":2376,"x":13,"y":5,"ans":"N20*******"},{"page":2376,"x":13,"y":6,"ans":"100,000"},{"page":2376,"x":13,"y":7,"ans":""},{"page":2376,"x":13,"y":9,"ans":"\u5f70\u5316\u7e23\u793e\u982d\u9109"},{"page":2376,"x":14,"y":2,"ans":"100\/12\/02"},{"page":2376,"x":14,"y":3,"ans":"\u500b\u4eba\u6350\u8d08\u6536\u5165"},{"page":2376,"x":14,"y":4,"ans":""},{"page":2376,"x":14,"y":5,"ans":"N22*******"},{"page":2376,"x":14,"y":6,"ans":"50,000"},{"page":2376,"x":14,"y":7,"ans":""},{"page":2376,"x":14,"y":9,"ans":"\u5f70\u5316\u7e23\u798f\u8208\u9109"},{"page":2376,"x":15,"y":2,"ans":"100\/12\/02"},{"page":2376,"x":15,"y":3,"ans":"\u500b\u4eba\u6350\u8d08\u6536\u5165"},{"page":2376,"x":15,"y":4,"ans":"\u8b1d\u6728\u6751"},{"page":2376,"x":15,"y":5,"ans":"N12*******"},{"page":2376,"x":15,"y":6,"ans":"50,000"},{"page":2376,"x":15,"y":7,"ans":""},{"page":2376,"x":15,"y":9,"ans":"\u5f70\u5316\u7e23\u9e7f\u6e2f\u93ae"},{"page":2376,"x":16,"y":2,"ans":"100\/12\/02"},{"page":2376,"x":16,"y":3,"ans":"\u500b\u4eba\u6350\u8d08\u6536\u5165"},{"page":2376,"x":16,"y":4,"ans":"\u5289\u660e\u677e"},{"page":2376,"x":16,"y":5,"ans":"N12*******"},{"page":2376,"x":16,"y":6,"ans":"20,000"},{"page":2376,"x":16,"y":7,"ans":""},{"page":2376,"x":16,"y":9,"ans":"\u5f70\u5316\u7e23\u9e7f\u6e2f\u93ae"},{"page":2376,"x":17,"y":2,"ans":"100\/12\/02"},{"page":2376,"x":17,"y":3,"ans":"\u500b\u4eba\u6350\u8d08\u6536\u5165"},{"page":2376,"x":17,"y":4,"ans":"\u9ec3\u6c5f\u6d5a"},{"page":2376,"x":17,"y":5,"ans":"N12\uff0a\uff0a\uff0a\uff0a\uff0a\uff0a\uff0a"},{"page":2376,"x":17,"y":6,"ans":"20,000"},{"page":2376,"x":17,"y":7,"ans":""},{"page":2376,"x":17,"y":9,"ans":"\u5f70\u5316\u7e23\u9e7f\u6e2f\u93ae"},{"page":2376,"x":18,"y":2,"ans":"100\/12\/02"},{"page":2376,"x":18,"y":3,"ans":"\u500b\u4eba\u6350\u8d08\u6536\u5165"},{"page":2376,"x":18,"y":4,"ans":"\u5085\u51f1\u7433"},{"page":2376,"x":18,"y":5,"ans":"N22*******"},{"page":2376,"x":18,"y":6,"ans":"6,000"},{"page":2376,"x":18,"y":7,"ans":""},{"page":2376,"x":18,"y":9,"ans":"\u5f70\u5316\u7e23\u5f70\u5316\u5e02"},{"page":2376,"x":19,"y":2,"ans":"100\/12\/01"},{"page":2376,"x":19,"y":3,"ans":"\u500b\u4eba\u6350\u8d08\u6536\u5165"},{"page":2376,"x":19,"y":4,"ans":"\u8b1d\u6587\u5fe0"},{"page":2376,"x":19,"y":5,"ans":"N100*******"},{"page":2376,"x":19,"y":6,"ans":"50000"},{"page":2376,"x":19,"y":7,"ans":""},{"page":2376,"x":19,"y":9,"ans":"\u5f70\u5316\u7e23\u7dda\u897f\u9109"},{"page":2376,"x":20,"y":2,"ans":"100\/12\/01"},{"page":2376,"x":20,"y":3,"ans":"\u500b\u4eba\u6350\u8d08\u6536\u5165"},{"page":2376,"x":20,"y":4,"ans":"\u65c5\u745e\u6e90"},{"page":2376,"x":20,"y":5,"ans":"N12*******"},{"page":2376,"x":20,"y":6,"ans":"6000"},{"page":2376,"x":20,"y":7,"ans":""},{"page":2376,"x":20,"y":9,"ans":"\u5f70\u5316\u7e23\u9e7f\u6e2f\u93ae"},{"page":2376,"x":21,"y":2,"ans":"100\/12\/01"},{"page":2376,"x":21,"y":3,"ans":"\u500b\u4eba\u6350\u8d08\u6536\u5165"},{"page":2376,"x":21,"y":4,"ans":"\u8b1d\u6d77\u745e"},{"page":2376,"x":21,"y":5,"ans":"N10*******"},{"page":2376,"x":21,"y":6,"ans":"10,000"},{"page":2376,"x":21,"y":7,"ans":""},{"page":2376,"x":21,"y":9,"ans":"\u5f70\u5316\u7e23\u7dda\u897f\u9109"}]