[{"page":2468,"x":2,"y":2,"ans":"100\/11\/12"},{"page":2468,"x":2,"y":3,"ans":"\u500b\u4eba\u6350\u8d08\u6536\u5165"},{"page":2468,"x":2,"y":4,"ans":"\u5433\u6625\u660e"},{"page":2468,"x":2,"y":5,"ans":"F10*******"},{"page":2468,"x":2,"y":6,"ans":"30,000"},{"page":2468,"x":2,"y":7,"ans":""},{"page":2468,"x":2,"y":9,"ans":"\u65b0\u5317\u5e02\u677f\u6a4b\u5340"},{"page":2468,"x":3,"y":2,"ans":"100\/11\/12"},{"page":2468,"x":3,"y":3,"ans":"\u500b\u4eba\u6350\u8d08\u6536\u5165"},{"page":2468,"x":3,"y":4,"ans":"\u4f55\u65fb\u5fe0"},{"page":2468,"x":3,"y":5,"ans":"K12*******"},{"page":2468,"x":3,"y":6,"ans":"3000"},{"page":2468,"x":3,"y":7,"ans":""},{"page":2468,"x":3,"y":9,"ans":"\u81fa\u5317\u5e02\u5317\u6295\u5340"},{"page":2468,"x":4,"y":2,"ans":"100\/11\/12"},{"page":2468,"x":4,"y":3,"ans":"\u500b\u4eba\u6350\u8d08\u6536\u5165"},{"page":2468,"x":4,"y":4,"ans":"\u9b4f\u61b2\u5a1f"},{"page":2468,"x":4,"y":5,"ans":"Y22*******"},{"page":2468,"x":4,"y":6,"ans":"500"},{"page":2468,"x":4,"y":7,"ans":""},{"page":2468,"x":4,"y":9,"ans":"\u53f0\u5317\u5e02\u7acb\u8fb2\u8857"},{"page":2468,"x":5,"y":2,"ans":"100\/11\/12"},{"page":2468,"x":5,"y":3,"ans":"\u500b\u4eba\u6350\u8d08\u6536\u5165"},{"page":2468,"x":5,"y":4,"ans":"\u6c88\u5408\u6885"},{"page":2468,"x":5,"y":5,"ans":"J20*******"},{"page":2468,"x":5,"y":6,"ans":"2,000"},{"page":2468,"x":5,"y":7,"ans":""},{"page":2468,"x":5,"y":9,"ans":"\u81fa\u5317\u5e02\u5317\u6295\u5340"},{"page":2468,"x":6,"y":2,"ans":"100\/11\/12"},{"page":2468,"x":6,"y":3,"ans":"\u500b\u4eba\u6350\u8d08\u6536\u5165"},{"page":2468,"x":6,"y":4,"ans":"\u5468\u99a5\u6885"},{"page":2468,"x":6,"y":5,"ans":"A20*******"},{"page":2468,"x":6,"y":6,"ans":"2000"},{"page":2468,"x":6,"y":7,"ans":""},{"page":2468,"x":6,"y":9,"ans":"\u81fa\u5317\u5e02\u5317\u6295\u5340"},{"page":2468,"x":7,"y":2,"ans":"100\/11\/12"},{"page":2468,"x":7,"y":3,"ans":"\u500b\u4eba\u6350\u8d08\u6536\u5165"},{"page":2468,"x":7,"y":4,"ans":"\u6797\u69ae\u6e05"},{"page":2468,"x":7,"y":5,"ans":"S12*******"},{"page":2468,"x":7,"y":6,"ans":"6,000"},{"page":2468,"x":7,"y":7,"ans":""},{"page":2468,"x":7,"y":9,"ans":"\u81fa\u5317\u5e02\u5317\u6295\u5340"},{"page":2468,"x":8,"y":2,"ans":"100\/11\/12"},{"page":2468,"x":8,"y":3,"ans":"\u500b\u4eba\u6350\u8d08\u6536\u5165"},{"page":2468,"x":8,"y":4,"ans":"\u738b\u9d3b\u5112"},{"page":2468,"x":8,"y":5,"ans":"H12*******"},{"page":2468,"x":8,"y":6,"ans":"2,000"},{"page":2468,"x":8,"y":7,"ans":""},{"page":2468,"x":8,"y":9,"ans":"\u53f0\u5317\u5e02\u5357\u6e2f\u5340"},{"page":2468,"x":9,"y":2,"ans":"100\/11\/12"},{"page":2468,"x":9,"y":3,"ans":"\u500b\u4eba\u6350\u8d08\u6536\u5165"},{"page":2468,"x":9,"y":4,"ans":"\u9673\u5349\u7f9a"},{"page":2468,"x":9,"y":5,"ans":"A22*******"},{"page":2468,"x":9,"y":6,"ans":"3000"},{"page":2468,"x":9,"y":7,"ans":""},{"page":2468,"x":9,"y":9,"ans":"\u81fa\u5317\u5e02\u5317\u6295\u5340"},{"page":2468,"x":10,"y":2,"ans":"100\/11\/12"},{"page":2468,"x":10,"y":3,"ans":"\u500b\u4eba\u6350\u8d08\u6536\u5165"},{"page":2468,"x":10,"y":4,"ans":"\u767d\u5efa\u667a"},{"page":2468,"x":10,"y":5,"ans":""},{"page":2468,"x":10,"y":6,"ans":"1,000"},{"page":2468,"x":10,"y":7,"ans":""},{"page":2468,"x":10,"y":9,"ans":"\u81fa\u5317\u5e02\u5317\u6295\u5340"},{"page":2468,"x":11,"y":2,"ans":"100\/11\/12"},{"page":2468,"x":11,"y":3,"ans":"\u500b\u4eba\u6350\u8d08\u6536\u5165"},{"page":2468,"x":11,"y":4,"ans":"\u5289\u8208\u660e"},{"page":2468,"x":11,"y":5,"ans":"A10*******"},{"page":2468,"x":11,"y":6,"ans":"10,000"},{"page":2468,"x":11,"y":7,"ans":""},{"page":2468,"x":11,"y":9,"ans":"\u81fa\u5317\u5e02\u5317\u6295\u5340"},{"page":2468,"x":12,"y":2,"ans":"100\/11\/12"},{"page":2468,"x":12,"y":3,"ans":"\u500b\u4eba\u6350\u8d08\u6536\u5165"},{"page":2468,"x":12,"y":4,"ans":"\u6797\u6839\u5f18"},{"page":2468,"x":12,"y":5,"ans":"G10*******"},{"page":2468,"x":12,"y":6,"ans":"10,000"},{"page":2468,"x":12,"y":7,"ans":""},{"page":2468,"x":12,"y":9,"ans":"\u81fa\u5317\u5e02\u5317\u6295\u5340"},{"page":2468,"x":13,"y":2,"ans":"100\/11\/12"},{"page":2468,"x":13,"y":3,"ans":"\u500b\u4eba\u6350\u8d08\u6536\u5165"},{"page":2468,"x":13,"y":4,"ans":"\u962e\u963f\u93d7"},{"page":2468,"x":13,"y":5,"ans":"Y10*******"},{"page":2468,"x":13,"y":6,"ans":"5,000"},{"page":2468,"x":13,"y":7,"ans":""},{"page":2468,"x":13,"y":9,"ans":"\u81fa\u5317\u5e02\u5317\u6295\u5340"},{"page":2468,"x":14,"y":2,"ans":"100\/11\/12"},{"page":2468,"x":14,"y":3,"ans":"\u500b\u4eba\u6350\u8d08\u6536\u5165"},{"page":2468,"x":14,"y":4,"ans":"\u7f85\u5bb6\u715c"},{"page":2468,"x":14,"y":5,"ans":"Q10*******"},{"page":2468,"x":14,"y":6,"ans":"5,000"},{"page":2468,"x":14,"y":7,"ans":""},{"page":2468,"x":14,"y":9,"ans":"\u81fa\u5317\u5e02\u5317\u6295\u5340"},{"page":2468,"x":15,"y":2,"ans":"100\uff0f11\uff0f12"},{"page":2468,"x":15,"y":3,"ans":"\u500b\u4eba\u6350\u8d08\u6536\u5165"},{"page":2468,"x":15,"y":4,"ans":"\u674e\u5b78\u653f"},{"page":2468,"x":15,"y":5,"ans":"Q10*******"},{"page":2468,"x":15,"y":6,"ans":"20,000"},{"page":2468,"x":15,"y":7,"ans":""},{"page":2468,"x":15,"y":9,"ans":"\u81fa\u5317\u5e02\u58eb\u6797\u5340"},{"page":2468,"x":16,"y":2,"ans":"100\/11\/12"},{"page":2468,"x":16,"y":3,"ans":"\u500b\u4eba\u6350\u8d08\u6536\u5165"},{"page":2468,"x":16,"y":4,"ans":"\u9673\u771f\u5fd7"},{"page":2468,"x":16,"y":5,"ans":"L20*******"},{"page":2468,"x":16,"y":6,"ans":"500"},{"page":2468,"x":16,"y":7,"ans":""},{"page":2468,"x":16,"y":9,"ans":"\u81fa\u5317\u5e02\u5317\u6295\u5340"},{"page":2468,"x":17,"y":2,"ans":"100\/11\/12"},{"page":2468,"x":17,"y":3,"ans":"\u500b\u4eba\u6350\u8d08\u6536\u5165"},{"page":2468,"x":17,"y":4,"ans":"\u9673\u5fd7\u5cf0"},{"page":2468,"x":17,"y":5,"ans":"K12*******"},{"page":2468,"x":17,"y":6,"ans":"50,000"},{"page":2468,"x":17,"y":7,"ans":""},{"page":2468,"x":17,"y":9,"ans":"\u81fa\u5357\u5e02\u4e2d\u83ef\u6771"},{"page":2468,"x":18,"y":2,"ans":"100\/11\/12"},{"page":2468,"x":18,"y":3,"ans":"\u500b\u4eba\u6350\u8d08\u6536\u5165"},{"page":2468,"x":18,"y":4,"ans":"\u77f3\u5e2b\u8aa0"},{"page":2468,"x":18,"y":5,"ans":"A10\uff0a\uff0a\uff0a\uff0a\uff0a\uff0a\uff0a"},{"page":2468,"x":18,"y":6,"ans":"2,000"},{"page":2468,"x":18,"y":7,"ans":""},{"page":2468,"x":18,"y":9,"ans":""},{"page":2468,"x":19,"y":2,"ans":"100\/11\/12"},{"page":2468,"x":19,"y":3,"ans":"\u500b\u4eba\u6350\u8d08\u6536\u5165"},{"page":2468,"x":19,"y":4,"ans":"\u5289\u671d\u7d05"},{"page":2468,"x":19,"y":5,"ans":"B10*******"},{"page":2468,"x":19,"y":6,"ans":"3,600"},{"page":2468,"x":19,"y":7,"ans":""},{"page":2468,"x":19,"y":9,"ans":"\u65b0\u5317\u5e02\u4e09\u91cd\u5340"},{"page":2468,"x":20,"y":2,"ans":"100\/11\/12"},{"page":2468,"x":20,"y":3,"ans":"\u500b\u4eba\u6350\u8d08\u6536\u5165"},{"page":2468,"x":20,"y":4,"ans":"\u984f\u5927\u5cf0"},{"page":2468,"x":20,"y":5,"ans":"F10*******"},{"page":2468,"x":20,"y":6,"ans":"12,000"},{"page":2468,"x":20,"y":7,"ans":""},{"page":2468,"x":20,"y":9,"ans":"\u81fa\u5317\u5e02\u5317\u6295\u5340"},{"page":2468,"x":21,"y":2,"ans":"100\/11\/12"},{"page":2468,"x":21,"y":3,"ans":"\u500b\u4eba\u6350\u8d08\u6536\u5165"},{"page":2468,"x":21,"y":4,"ans":"\u9673\u6c38\u5982"},{"page":2468,"x":21,"y":5,"ans":"Y12*******"},{"page":2468,"x":21,"y":6,"ans":"2,000"},{"page":2468,"x":21,"y":7,"ans":""},{"page":2468,"x":21,"y":9,"ans":"\u81fa\u5317\u5e02\u5317\u6295\u5340"}]